aixd/__init__.py
aixd/__main__.py
aixd/__version__.py
aixd/data/__init__.py
aixd/data/constants.py
aixd/data/custom_callbacks.py
aixd/data/data_blocks.py
aixd/data/data_objects.py
aixd/data/dataset.py
aixd/data/default_importer.py
aixd/data/domain.py
aixd/data/encoders.py
aixd/data/transform.py
aixd/data/utils_data.py
aixd/mlmodel/__init__.py
aixd/mlmodel/constants.py
aixd/mlmodel/utils_mlmodel.py
aixd/mlmodel/architecture/__init__.py
aixd/mlmodel/architecture/blocks.py
aixd/mlmodel/architecture/cond_ae_model.py
aixd/mlmodel/architecture/cond_vae_model.py
aixd/mlmodel/architecture/decoders.py
aixd/mlmodel/architecture/encoders.py
aixd/mlmodel/architecture/encodings.py
aixd/mlmodel/architecture/heads.py
aixd/mlmodel/architecture/losses.py
aixd/mlmodel/architecture/postprocessors.py
aixd/mlmodel/architecture/two_stage_model.py
aixd/mlmodel/data/__init__.py
aixd/mlmodel/data/data_loader.py
aixd/mlmodel/generation/__init__.py
aixd/mlmodel/generation/generator.py
aixd/mlmodel/generation/sampling.py
aixd/mlmodel/sensitivity/__init__.py
aixd/mlmodel/sensitivity/sensitivities.py
aixd/sampler/__init__.py
aixd/sampler/callbacks.py
aixd/sampler/constants.py
aixd/sampler/engines.py
aixd/sampler/operators.py
aixd/sampler/reducers.py
aixd/sampler/sampler.py
aixd/sampler/sampler_definitions.py
aixd/sampler/strategies.py
aixd/utils/__init__.py
aixd/utils/logger.yaml
aixd/utils/logs.py
aixd/utils/utils.py
aixd/visualisation/__init__.py
aixd/visualisation/plotter.py
aixd/visualisation/styles.py
aixd/visualisation/utils_plots.py
aixd-0.13.0.dist-info/AUTHORS.md
aixd-0.13.0.dist-info/LICENSE
aixd-0.13.0.dist-info/METADATA
aixd-0.13.0.dist-info/WHEEL
aixd-0.13.0.dist-info/top_level.txt
aixd-0.13.0.dist-info/RECORD
