Metadata-Version: 2.1
Name: aixd
Version: 0.13.0
Summary: AI-eXtended Design (AIXD)
Home-page: https://gitlab.renkulab.io/ai-augmented-design/aixd
Author: Apolinarska, Aleksandra; Bischof, Rafael; Casas, Gonzalo; Kraus, Michael; Kuhn, Sophia; Maissen, Alessandro; Rust, Romana; Salamanca, Luis; Tatsis, Konstantinos
Author-email: sluis@ethz.ch
License: MIT license
Classifier: Development Status :: 3 - Alpha
Classifier: Intended Audience :: Developers
Classifier: Intended Audience :: Science/Research
Classifier: License :: OSI Approved :: MIT License
Classifier: Operating System :: Unix
Classifier: Operating System :: POSIX
Classifier: Operating System :: Microsoft :: Windows
Classifier: Programming Language :: Python :: 3.9
Classifier: Programming Language :: Python :: Implementation :: CPython
Classifier: Topic :: Scientific/Engineering
License-File: LICENSE
License-File: AUTHORS.md
Requires-Dist: pandas (>=2.1.0)
Requires-Dist: numpy (>=1.22.4)
Requires-Dist: scipy (>=1.8.1)
Requires-Dist: scikit-learn (>=0.23.0)
Requires-Dist: plotly (~=6.0.0)
Requires-Dist: torch (>=2.0.0)
Requires-Dist: wandb
Requires-Dist: pytorch-lightning (>=2.0.0)
Requires-Dist: bayesian-optimization (<2.0.0)
Requires-Dist: coolname
Provides-Extra: dev
Requires-Dist: black[jupyter] ; extra == 'dev'
Requires-Dist: bump2version (>=1.0.1) ; extra == 'dev'
Requires-Dist: compas-invocations (>=1.0.0) ; extra == 'dev'
Requires-Dist: flake8 ; extra == 'dev'
Requires-Dist: invoke (>=0.14) ; extra == 'dev'
Requires-Dist: isort ; extra == 'dev'
Requires-Dist: nbsphinx ; extra == 'dev'
Requires-Dist: nbmake ; extra == 'dev'
Requires-Dist: nb-clean ; extra == 'dev'
Requires-Dist: pytest (>=6.0) ; extra == 'dev'
Requires-Dist: pytest-env ; extra == 'dev'
Requires-Dist: pytest-xdist ; extra == 'dev'
Requires-Dist: sphinx ; extra == 'dev'
Requires-Dist: pydata-sphinx-theme ; extra == 'dev'
Requires-Dist: check-manifest (>=0.36) ; extra == 'dev'
Requires-Dist: scp ; extra == 'dev'
Requires-Dist: paramiko ; extra == 'dev'
Provides-Extra: examples
Requires-Dist: jupyter ; extra == 'examples'
Requires-Dist: ipython (>=5.8) ; extra == 'examples'
Requires-Dist: ipykernel ; extra == 'examples'
Requires-Dist: pythreejs ; extra == 'examples'
Requires-Dist: matplotlib ; extra == 'examples'
Requires-Dist: rich (>=10.2.2) ; extra == 'examples'
